condensedinlinepanel/__init__.py
condensedinlinepanel/edit_handlers.py
condensedinlinepanel/wagtail_hooks.py
condensedinlinepanel/locale/es/LC_MESSAGES/django.mo
condensedinlinepanel/locale/es/LC_MESSAGES/django.po
condensedinlinepanel/locale/tr/LC_MESSAGES/django.mo
condensedinlinepanel/locale/tr/LC_MESSAGES/django.po
condensedinlinepanel/static/condensedinlinepanel/dist/.gitignore
condensedinlinepanel/static/condensedinlinepanel/dist/condensedinlinepanel.bundle.js
condensedinlinepanel/static/condensedinlinepanel/dist/condensedinlinepanel.css
condensedinlinepanel/static/condensedinlinepanel/src/condensedinlinepanel.tsx
condensedinlinepanel/static/condensedinlinepanel/src/state.ts
condensedinlinepanel/static/condensedinlinepanel/src/types.ts
condensedinlinepanel/static/condensedinlinepanel/src/components/Card.tsx
condensedinlinepanel/static/condensedinlinepanel/src/components/CardSet.tsx
condensedinlinepanel/static/condensedinlinepanel/src/components/FormContainer.tsx
condensedinlinepanel/static/condensedinlinepanel/src/components/Gap.tsx
condensedinlinepanel/templates/condensedinlinepanel/condensedinlinepanel.html
condensedinlinepanel/templates/condensedinlinepanel/condensedinlinepanel.js
wagtail_condensedinlinepanel-0.5.3.dist-info/METADATA
wagtail_condensedinlinepanel-0.5.3.dist-info/WHEEL
wagtail_condensedinlinepanel-0.5.3.dist-info/top_level.txt
wagtail_condensedinlinepanel-0.5.3.dist-info/RECORD
